{"2004-10": {"Total Votes": 9849.0, "Parties": ["botswana democratic party", "botswana national front", "botswana congress party", "botswana peoples party"], "Percent": [0.6181338206924561, 0.1618438420144177, 0.13179002944461365, 0.08823230784851253]}, "1979-10": {"Total Votes": 482.0, "Parties": ["botswana peoples party"], "Percent": [1.0]}, "2009-10": {"Total Votes": 0, "Parties": [], "Percent": []}, "1994-10": {"Total Votes": 102672.0, "Parties": ["Botswana Democratic Party", "Botswana National Front", "Botswana People\u2019s Party", "Independence Freedom Party", "United Socialist Party", "United Democratic Front"], "Percent": [0.5598897459872214, 0.39110955275050646, 0.03717664017453639, 0.008921614461586411, 0.0025810347514414835, 0.0003214118747078074]}, "1974-10": {"Total Votes": 4748.0, "Parties": ["botswana democratic party", "botswana peoples party"], "Percent": [0.7076663858466723, 0.2923336141533277]}, "1999-10": {"Total Votes": 18031.0, "Parties": ["botswana democratic party", "botswana congress party", "botswana national front"], "Percent": [0.5900948366701791, 0.23820087626864844, 0.17170428706117244]}, "1984-9": {"Total Votes": 10286.0, "Parties": ["botswana democratic party", "botswana peoples party", "botswana national front"], "Percent": [0.5726229826949252, 0.36933696286214274, 0.05804005444293214]}, "1969-10": {"Total Votes": 2011.0, "Parties": ["botswana democratic party", "botswana peoples party"], "Percent": [0.5062158130283441, 0.4937841869716559]}, "1989-10": {"Total Votes": 984.0, "Parties": ["Botswana National Front"], "Percent": [1.0]}}