{"2011-11": {"Total Votes": 0, "Parties": [], "Percent": []}, "1984-0": {"Total Votes": 0, "Parties": [], "Percent": []}, "1972-0": {"Total Votes": 0, "Parties": [], "Percent": []}, "1960-0": {"Total Votes": 0, "Parties": [], "Percent": []}, "1966-0": {"Total Votes": 0, "Parties": [], "Percent": []}, "1978-0": {"Total Votes": 0, "Parties": [], "Percent": []}, "1987-0": {"Total Votes": 0, "Parties": [], "Percent": []}, "2005-9": {"Total Votes": 0, "Parties": [], "Percent": []}, "1999-11": {"Total Votes": 0, "Parties": [], "Percent": []}, "2008-11": {"Total Votes": 0, "Parties": [], "Percent": []}, "1963-0": {"Total Votes": 0, "Parties": [], "Percent": []}, "2002-7": {"Total Votes": 0, "Parties": [], "Percent": []}, "1946-0": {"Total Votes": 11912.0, "Parties": ["national", "labour"], "Percent": [0.5086467427803896, 0.4913532572196105]}, "1957-0": {"Total Votes": 0, "Parties": [], "Percent": []}, "1975-0": {"Total Votes": 0, "Parties": [], "Percent": []}, "1981-0": {"Total Votes": 0, "Parties": [], "Percent": []}, "1954-0": {"Total Votes": 0, "Parties": [], "Percent": []}, "1949-0": {"Total Votes": 11681.0, "Parties": ["national", "labour", "communist"], "Percent": [0.535484975601404, 0.4533002311445938, 0.011214793254002226]}, "1969-0": {"Total Votes": 0, "Parties": [], "Percent": []}, "1951-0": {"Total Votes": 11123.0, "Parties": ["national", "labour"], "Percent": [0.5713386676256406, 0.42866133237435944]}}