{"Tunisia": {"1880": [[], [], [], [], []], "1899": [[], [], [], [], []], "2009": [[1234310400000, 1238198400000, 1243468800000, 1244246400000, 1245456000000, 1250035200000, 1252195200000, 1255219200000, 1255478400000, 1258156800000], [1524, 1537, 1544, 1553, 1553, 1554, 1563, 1567, 1557, 1528], ["Tunisia - Netherlands", "Kenya - Tunisia", "Tunisia - Sudan", "Tunisia - Mozambique", "Tunisia - Nigeria", "Tunisia - C\u00f4te d'Ivoire", "Nigeria - Tunisia", "Tunisia - Kenya", "Tunisia - Saudi Arabia", "Mozambique - Tunisia"], ["1 - 1", "1 - 2", "4 - 0", "2 - 0", "0 - 0", "0 - 0", "2 - 2", "1 - 0", "0 - 1", "1 - 0"], ["Friendly", "FIFA World Cup\u2122 Qualifier", "Friendly", "FIFA World Cup\u2122 Qualifier", "FIFA World Cup\u2122 Qualifier", "Friendly", "FIFA World Cup\u2122 Qualifier", "FIFA World Cup\u2122 Qualifier", "Friendly", "FIFA World Cup\u2122 Qualifier"]], "1892": [[], [], [], [], []], "1897": [[], [], [], [], []], "2002": [[1010707200000, 1011571200000, 1011916800000, 1012435200000, 1015977600000, 1017187200000, 1019001600000, 1022371200000, 1023235200000, 1023667200000, 1024012800000, 1029888000000, 1034380800000, 1037750400000], [1570, 1557, 1528, 1529, 1529, 1529, 1521, 1517, 1484, 1500, 1485, 1491, 1498, 1497], ["Tunisia - Cameroon", "Tunisia - Zambia", "Egypt - Tunisia", "Senegal - Tunisia", "Tunisia - Korea Republic", "Tunisia - Norway", "Slovenia - Tunisia", "Denmark - Tunisia", "Russia - Tunisia", "Tunisia - Belgium", "Tunisia - Japan", "Tunisia - France", "Portugal - Tunisia", "Tunisia - Egypt"], ["0 - 1", "0 - 0", "1 - 0", "0 - 0", "0 - 0", "0 - 0", "1 - 0", "2 - 1", "2 - 0", "1 - 1", "0 - 2", "1 - 1", "1 - 1", "0 - 0"], ["Friendly", "Continental Final", "Continental Final", "Continental Final", "Friendly", "Friendly", "Friendly", "Friendly", "FIFA World Cup\u2122 Final", "FIFA World Cup\u2122 Final", "FIFA World Cup\u2122 Final", "Friendly", "Friendly", "Friendly"]], "1991": [[668131200000, 670032000000, 670982400000, 671587200000, 672796800000, 680486400000, 691200000000, 693619200000], [1356, 1357, 1363, 1366, 1363, 1374, 1394, 1397], ["Algeria - Tunisia", "Tunisia - Turkey", "Tunisia - Algeria", "Tunisia - Egypt", "Chad - Tunisia", "Egypt - Tunisia", "Tunisia - C\u00f4te d'Ivoire", "Tunisia - Cameroon"], ["2 - 1", "0 - 0", "0 - 0", "2 - 2", "0 - 0", "2 - 2", "5 - 3", "2 - 2"], ["Friendly", "Friendly", "Friendly", "Continental Qualifier", "Continental Qualifier", "Continental Qualifier", "Friendly", "Friendly"]], "1890": [[], [], [], [], []], "1908": [[], [], [], [], []], "1928": [[], [], [], [], []], "1938": [[], [], [], [], []], "1879": [[], [], [], [], []], "1993": [[726624000000, 727228800000, 728438400000, 730857600000, 732326400000, 748656000000, 750816000000, 752457600000, 752630400000, 757296000000], [1436, 1449, 1460, 1465, 1459, 1465, 1476, 1486, 1500, 1492], ["Tunisia - Bulgaria", "Benin - Tunisia", "Tunisia - Ethiopia", "Morocco - Tunisia", "Tunisia - Switzerland", "Tunisia - Germany", "Tunisia - Iceland", "Tunisia - Gabon", "Tunisia - Egypt", "Ghana - Tunisia"], ["3 - 0", "0 - 5", "3 - 0", "0 - 0", "0 - 1", "1 - 1", "3 - 1", "4 - 0", "2 - 0", "2 - 1"], ["Friendly", "FIFA World Cup\u2122 Qualifier", "FIFA World Cup\u2122 Qualifier", "FIFA World Cup\u2122 Qualifier", "Friendly", "Friendly", "Friendly", "Friendly", "Friendly", "Friendly"]], "1980": [[317779200000, 318038400000, 320457600000, 323740800000, 329270400000, 331084800000, 332208000000, 342662400000], [1523, 1521, 1521, 1531, 1518, 1543, 1518, 1512], ["Ghana - Tunisia", "C\u00f4te d'Ivoire - Tunisia", "Morocco - Tunisia", "Senegal - Tunisia", "Tunisia - Morocco", "Tunisia - Nigeria", "Nigeria - Tunisia", "Angola - Tunisia"], ["4 - 1", "1 - 1", "0 - 0", "0 - 2", "0 - 1", "2 - 0", "2 - 0", "1 - 1"], ["Friendly", "Friendly", "Friendly", "Friendly", "Friendly", "FIFA World Cup\u2122 Qualifier", "FIFA World Cup\u2122 Qualifier", "Friendly"]], "1968": [[-56937600000, -35424000000, -34819200000, -34214400000, -31795200000], [1312, 1339, 1329, 1313, 1309], ["Turkey - Tunisia", "Algeria - Tunisia", "Congo DR - Tunisia", "Cameroon - Tunisia", "Tunisia - Algeria"], ["0 - 0", "1 - 2", "1 - 0", "4 - 2", "0 - 0"], ["Friendly", "FIFA World Cup\u2122 Qualifier", "Friendly", "Friendly", "FIFA World Cup\u2122 Qualifier"]], "1987": [[537321600000, 543801600000, 545184000000, 554774400000, 554947200000, 555120000000, 555379200000, 559353600000, 565401600000], [1436, 1426, 1428, 1414, 1385, 1373, 1363, 1359, 1348], ["Tunisia - Algeria", "Algeria - Tunisia", "Tunisia - Algeria", "Kenya - Tunisia", "Tunisia - Madagascar", "Tunisia - Cameroon", "Tunisia - Senegal", "German DR - Tunisia", "Tunisia - Malawi"], ["0 - 2", "1 - 0", "1 - 1", "1 - 0", "0 - 3", "1 - 3", "0 - 1", "2 - 0", "2 - 3"], ["Friendly", "Continental Qualifier", "Continental Qualifier", "Friendly", "Friendly", "Friendly", "Friendly", "Friendly", "Friendly"]], "1974": [[126662400000, 131068800000, 137462400000, 139363200000, 149472000000, 149558400000, 149817600000, 150163200000, 150336000000, 150508800000, 153273600000, 154310400000], [1395, 1389, 1399, 1409, 1430, 1418, 1403, 1414, 1399, 1413, 1420, 1393], ["Mali - Tunisia", "Tunisia - German DR", "Algeria - Tunisia", "Tunisia - Iraq", "Egypt - Tunisia", "Lebanon - Tunisia", "Tunisia - Morocco", "Jordan - Tunisia", "Syria - Tunisia", "Sudan - Tunisia", "Tunisia - Libya", "Libya - Tunisia"], ["1 - 0", "0 - 4", "1 - 2", "2 - 1", "0 - 2", "2 - 1", "1 - 3", "0 - 5", "3 - 1", "1 - 3", "1 - 0", "1 - 0"], ["Friendly", "Friendly", "Friendly", "Friendly", "Friendly", "Friendly", "Friendly", "Friendly", "Friendly", "Friendly", "Continental Qualifier", "Continental Qualifier"]], "1896": [[], [], [], [], []], "1882": [[], [], [], [], []], "1954": [[], [], [], [], []], "2012": [[1326067200000, 1326412800000, 1327276800000, 1327622400000, 1327968000000, 1328400000000, 1330473600000, 1338076800000, 1338595200000, 1339200000000, 1344988800000, 1347062400000, 1350086400000, 1350345600000, 1352851200000, 1356825600000], [1491, 1482, 1507, 1514, 1487, 1474, 1477, 1484, 1493, 1507, 1509, 1500, 1486, 1501, 1494, 1506], ["Tunisia - Sudan", "Tunisia - C\u00f4te d'Ivoire", "Morocco - Tunisia", "Niger - Tunisia", "Gabon - Tunisia", "Ghana - Tunisia", "Tunisia - Peru", "Tunisia - Rwanda", "Tunisia - Equatorial Guinea", "Cape Verde Islands - Tunisia", "Tunisia - Iran", "Sierra Leone - Tunisia", "Tunisia - Sierra Leone", "Egypt - Tunisia", "Tunisia - Switzerland", "Iraq - Tunisia"], ["3 - 0", "0 - 2", "1 - 2", "1 - 2", "1 - 0", "2 - 1", "1 - 1", "5 - 1", "3 - 1", "1 - 2", "2 - 2", "2 - 2", "0 - 0", "0 - 1", "1 - 2", "1 - 2"], ["Friendly", "Friendly", "Continental Final", "Continental Final", "Continental Final", "Continental Final", "Friendly", "Friendly", "FIFA World Cup\u2122 Qualifier", "FIFA World Cup\u2122 Qualifier", "Friendly", "Continental Qualifier", "Continental Qualifier", "Friendly", "Friendly", "Friendly"]], "1931": [[], [], [], [], []], "1923": [[], [], [], [], []], "1872": [[], [], [], [], []], "1951": [[], [], [], [], []], "1913": [[], [], [], [], []], "1918": [[], [], [], [], []], "2015": [[1421539200000, 1421884800000, 1422230400000, 1422662400000, 1427414400000, 1427760000000, 1434067200000, 1434067200000, 1434326400000, 1434326400000, 1434585600000, 1434585600000, 1441411200000, 1444348800000, 1445212800000, 1445731200000, 1447372800000, 1447718400000], [1535, 1554, 1543, 1503, 1496, 1498, 1499, 1499, 1500, 1500, 1485, 1487, 1456, 1453, 1459, 1448, 1462, 1467], ["Tunisia - Cape Verde Islands", "Zambia - Tunisia", "Congo DR - Tunisia", "Tunisia - Equatorial Guinea", "Japan - Tunisia", "China PR - Tunisia", "Tunisia - Djibouti", "Tunisia - Djibouti", "Morocco - Tunisia", "Morocco - Tunisia", "Tunisia - Libya", "Libya - Tunisia", "Liberia - Tunisia", "Tunisia - Gabon", "Tunisia - Libya", "Tunisia - Morocco", "Mauritania - Tunisia", "Tunisia - Mauritania"], ["1 - 1", "1 - 2", "1 - 1", "1 - 2", "2 - 0", "1 - 1", "8 - 1", "8 - 1", "1 - 1", "1 - 1", "0 - 1", "1 - 0", "1 - 0", "3 - 3", "1 - 0", "2 - 3", "1 - 2", "2 - 1"], ["Continental Final", "Continental Final", "Continental Final", "Continental Final", "Friendly", "Friendly", "Continental Qualifier", "Continental Qualifier", "Friendly", "Friendly", "Friendly", "Friendly", "Continental Qualifier", "Friendly", "Friendly", "Friendly", "Continental Qualifier", "Continental Qualifier"]], "1924": [[], [], [], [], []], "1932": [[], [], [], [], []], "1971": [[56073600000], [1311], ["Tunisia - Syria"], ["1 - 0"], ["Friendly"]], "1919": [[], [], [], [], []], "1945": [[], [], [], [], []], "1970": [[22982400000], [1302], ["Tunisia - Libya"], ["2 - 0"], ["Friendly"]], "1996": [[820627200000, 821059200000, 821750400000, 822009600000, 822528000000, 822787200000, 823046400000, 823305600000, 833068800000, 833673600000, 834883200000, 844560000000, 845164800000, 847584000000], [1423, 1416, 1410, 1395, 1445, 1442, 1494, 1468, 1476, 1488, 1493, 1503, 1498, 1511], ["Morocco - Tunisia", "Egypt - Tunisia", "Tunisia - Mozambique", "Ghana - Tunisia", "Tunisia - C\u00f4te d'Ivoire", "Gabon - Tunisia", "Zambia - Tunisia", "South Africa - Tunisia", "Tunisia - Senegal", "Rwanda - Tunisia", "Tunisia - Rwanda", "Tunisia - Sierra Leone", "Japan - Tunisia", "Liberia - Tunisia"], ["3 - 1", "2 - 1", "1 - 1", "2 - 1", "3 - 1", "1 - 1", "2 - 4", "2 - 0", "2 - 0", "1 - 3", "2 - 0", "2 - 0", "1 - 0", "0 - 1"], ["Friendly", "Friendly", "Continental Final", "Continental Final", "Continental Final", "Continental Final", "Continental Final", "Continental Final", "Friendly", "FIFA World Cup\u2122 Qualifier", "FIFA World Cup\u2122 Qualifier", "Continental Qualifier", "Friendly", "FIFA World Cup\u2122 Qualifier"]], "1910": [[], [], [], [], []], "1935": [[], [], [], [], []], "1957": [[], [], [], [], []], "1990": [[644284800000, 650160000000, 651024000000, 657936000000, 658281600000, 658886400000], [1331, 1333, 1343, 1331, 1323, 1358], ["Tunisia - England", "Tunisia - Morocco", "Tunisia - Chad", "Tunisia - Norway", "Tunisia - Finland", "Ethiopia - Tunisia"], ["1 - 1", "0 - 0", "2 - 1", "1 - 3", "1 - 2", "0 - 2"], ["Friendly", "Friendly", "Continental Qualifier", "Friendly", "Friendly", "Continental Qualifier"]], "1963": [[-215654400000, -215049600000, -212889600000, -212716800000, -212630400000, -212630400000, -212284800000, -212112000000, -211766400000, -211593600000, -211420800000, -206582400000, -205200000000, -197856000000, -197683200000, -192672000000, -192326400000, -190857600000], [1275, 1262, 1284, 1301, 1312, 1315, 1327, 1339, 1329, 1337, 1337, 1366, 1340, 1332, 1346, 1347, 1303, 1302], ["Tunisia - Kuwait", "C\u00f4te d'Ivoire - Tunisia", "Jordan - Tunisia", "Tunisia - Kuwait", "Tunisia - Syria", "Lebanon - Tunisia", "Tunisia - C\u00f4te d'Ivoire", "Tunisia - Congo", "Congo DR - Tunisia", "Tunisia - Madagascar", "Senegal - Tunisia", "Tunisia - Morocco", "Morocco - Tunisia", "Morocco - Tunisia", "Tunisia - Syria", "Ghana - Tunisia", "Ethiopia - Tunisia", "Tunisia - Algeria"], ["2 - 1", "3 - 0", "0 - 4", "5 - 1", "1 - 0", "0 - 1", "3 - 1", "2 - 0", "1 - 0", "2 - 1", "1 - 1", "4 - 1", "4 - 2", "1 - 0", "3 - 1", "1 - 1", "4 - 2", "0 - 0"], ["Friendly", "Friendly", "Friendly", "Friendly", "Friendly", "Friendly", "Friendly", "Friendly", "Friendly", "Friendly", "Friendly", "Continental Qualifier", "Continental Qualifier", "Friendly", "Friendly", "Continental Final", "Continental Final", "Friendly"]], "1885": [[], [], [], [], []], "1920": [[], [], [], [], []], "1937": [[], [], [], [], []], "1900": [[], [], [], [], []], "1884": [[], [], [], [], []], "1906": [[], [], [], [], []], "1976": [[193449600000, 194313600000, 212889600000, 216432000000, 217641600000, 219196800000], [1432, 1436, 1446, 1452, 1447, 1456], ["Tunisia - Yugoslavia", "Tunisia - Sweden", "Saudi Arabia - Tunisia", "Tunisia - Libya", "Malta - Tunisia", "Morocco - Tunisia"], ["2 - 1", "1 - 1", "0 - 1", "3 - 0", "1 - 1", "1 - 1"], ["Friendly", "Friendly", "Friendly", "Friendly", "Friendly", "FIFA World Cup\u2122 Qualifier"]], "2011": [[1301356800000, 1306627200000, 1307232000000, 1312934400000, 1313971200000, 1315008000000, 1318032000000, 1321056000000], [1470, 1474, 1480, 1490, 1490, 1485, 1495, 1483], ["Oman - Tunisia", "Tunisia - Central African Republic", "Tunisia - Chad", "Tunisia - Mali", "Jordan - Tunisia", "Malawi - Tunisia", "Tunisia - Togo", "Algeria - Tunisia"], ["2 - 1", "3 - 0", "5 - 0", "4 - 2", "3 - 3", "0 - 0", "2 - 0", "1 - 0"], ["Friendly", "Friendly", "Continental Qualifier", "Friendly", "Friendly", "Continental Qualifier", "Continental Qualifier", "Friendly"]], "1946": [[], [], [], [], []], "1898": [[], [], [], [], []], "1977": [[221616000000, 224035200000, 225936000000, 226368000000, 226627200000, 227664000000, 230083200000, 231292800000, 234316800000, 235526400000, 242352000000, 243993600000, 244598400000, 248140800000, 248486400000, 249264000000, 250646400000], [1455, 1469, 1464, 1447, 1435, 1426, 1432, 1448, 1438, 1472, 1475, 1472, 1505, 1528, 1511, 1492, 1518], ["Tunisia - Morocco", "Tunisia - Algeria", "Algeria - Tunisia", "Tunisia - Malta", "Qatar - Tunisia", "Tunisia - Soviet Union", "Egypt - Tunisia", "Tunisia - Egypt", "Guinea - Tunisia", "Tunisia - Guinea", "Tunisia - Malta", "Tunisia - Nigeria", "Tunisia - Guinea", "Nigeria - Tunisia", "Guinea - Tunisia", "Egypt - Tunisia", "Tunisia - Egypt"], ["1 - 1", "2 - 0", "1 - 1", "0 - 1", "1 - 0", "0 - 3", "2 - 2", "3 - 2", "1 - 0", "3 - 1", "2 - 1", "0 - 0", "3 - 0", "0 - 1", "3 - 2", "3 - 2", "4 - 1"], ["FIFA World Cup\u2122 Qualifier", "FIFA World Cup\u2122 Qualifier", "FIFA World Cup\u2122 Qualifier", "Friendly", "Friendly", "Friendly", "Continental Qualifier", "Continental Qualifier", "FIFA World Cup\u2122 Qualifier", "FIFA World Cup\u2122 Qualifier", "Friendly", "FIFA World Cup\u2122 Qualifier", "Continental Qualifier", "FIFA World Cup\u2122 Qualifier", "Continental Qualifier", "FIFA World Cup\u2122 Qualifier", "FIFA World Cup\u2122 Qualifier"]], "1925": [[], [], [], [], []], "1985": [[473385600000, 476841600000, 478051200000, 480902400000, 482284800000, 483753600000, 489456000000, 490665600000, 491356800000, 491961600000, 492220800000, 492480000000, 497404800000, 498441600000, 502848000000], [1469, 1444, 1457, 1431, 1447, 1458, 1441, 1465, 1475, 1479, 1480, 1484, 1449, 1434, 1449], ["Ghana - Tunisia", "Guinea - Tunisia", "Tunisia - Guinea", "Libya - Tunisia", "Tunisia - Libya", "Tunisia - Algeria", "Nigeria - Tunisia", "Tunisia - Nigeria", "Tunisia - Saudi Arabia", "Tunisia - Mauritania", "Morocco - Tunisia", "Somalia - Tunisia", "Tunisia - Algeria", "Algeria - Tunisia", "Tunisia - Poland"], ["0 - 2", "1 - 0", "2 - 0", "2 - 0", "1 - 0", "1 - 0", "1 - 0", "2 - 0", "1 - 0", "4 - 0", "2 - 2", "0 - 1", "1 - 4", "3 - 0", "1 - 0"], ["Friendly", "FIFA World Cup\u2122 Qualifier", "FIFA World Cup\u2122 Qualifier", "Continental Qualifier", "Continental Qualifier", "Friendly", "FIFA World Cup\u2122 Qualifier", "FIFA World Cup\u2122 Qualifier", "Friendly", "Friendly", "Friendly", "Friendly", "FIFA World Cup\u2122 Qualifier", "FIFA World Cup\u2122 Qualifier", "Friendly"]], "1965": [[-151545600000, -130550400000, -130377600000, -129772800000], [1294, 1343, 1341, 1328], ["Tunisia - Algeria", "Tunisia - Ethiopia", "Tunisia - Senegal", "Tunisia - Ghana"], ["0 - 0", "4 - 0", "0 - 0", "2 - 3"], ["Friendly", "Continental Final", "Continental Final", "Continental Final"]], "hoogste elo": 1674, "1916": [[], [], [], [], []], "1941": [[], [], [], [], []], "1907": [[], [], [], [], []], "1933": [[], [], [], [], []], "2014": [[1393977600000, 1401235200000, 1402099200000, 1409961600000, 1410307200000, 1412899200000, 1413331200000, 1415923200000, 1416355200000], [1473, 1489, 1485, 1492, 1520, 1524, 1539, 1529, 1544], ["Colombia - Tunisia", "Korea Republic - Tunisia", "Belgium - Tunisia", "Tunisia - Botswana", "Egypt - Tunisia", "Senegal - Tunisia", "Tunisia - Senegal", "Botswana - Tunisia", "Tunisia - Egypt"], ["1 - 1", "0 - 1", "1 - 0", "2 - 1", "0 - 1", "0 - 0", "1 - 0", "0 - 0", "2 - 1"], ["Friendly", "Friendly", "Friendly", "Continental Qualifier", "Continental Qualifier", "Continental Qualifier", "Continental Qualifier", "Continental Qualifier", "Continental Qualifier"]], "1922": [[], [], [], [], []], "1909": [[], [], [], [], []], "1986": [[530928000000], [1451], ["Tunisia - Bulgaria"], ["3 - 3"], ["Friendly"]], "1939": [[], [], [], [], []], "2010": [[1262995200000, 1263340800000, 1263686400000, 1264032000000, 1275177600000, 1276992000000, 1277942400000, 1281484800000, 1283558400000, 1286668800000, 1289952000000], [1512, 1506, 1505, 1515, 1520, 1528, 1492, 1504, 1490, 1505, 1479], ["Tunisia - Gambia", "Zambia - Tunisia", "Gabon - Tunisia", "Cameroon - Tunisia", "Tunisia - France", "Sudan - Tunisia", "Tunisia - Botswana", "Chad - Tunisia", "Tunisia - Malawi", "Togo - Tunisia", "Botswana - Tunisia"], ["1 - 2", "1 - 1", "0 - 0", "2 - 2", "1 - 1", "2 - 6", "0 - 1", "1 - 3", "2 - 2", "1 - 2", "1 - 0"], ["Friendly", "Continental Final", "Continental Final", "Continental Final", "Friendly", "Friendly", "Continental Qualifier", "Continental Qualifier", "Continental Qualifier", "Continental Qualifier", "Continental Qualifier"]], "1982": [[381888000000, 384134400000, 384480000000, 384739200000, 408153600000, 409104000000], [1505, 1501, 1447, 1425, 1432, 1423], ["Tunisia - Algeria", "Cameroon - Tunisia", "Libya - Tunisia", "Ghana - Tunisia", "Tunisia - Angola", "Tunisia - Algeria"], ["0 - 1", "1 - 1", "2 - 0", "1 - 0", "3 - 1", "0 - 1"], ["Friendly", "Continental Final", "Continental Final", "Continental Final", "Friendly", "Friendly"]], "1972": [[76550400000, 90720000000, 92620800000, 93398400000], [1326, 1315, 1308, 1348], ["Tunisia - Algeria", "Tunisia - Algeria", "Egypt - Tunisia", "Tunisia - Egypt"], ["3 - 1", "1 - 2", "2 - 1", "2 - 0"], ["Friendly", "Friendly", "FIFA World Cup\u2122 Qualifier", "FIFA World Cup\u2122 Qualifier"]], "1889": [[], [], [], [], []], "1984": [[465004800000, 467164800000, 467769600000, 469152000000, 473040000000, 473212800000], [1440, 1453, 1469, 1477, 1460, 1451], ["Tunisia - Nigeria", "Tunisia - Canada", "Benin - Tunisia", "Tunisia - Benin", "C\u00f4te d'Ivoire - Tunisia", "Algeria - Tunisia"], ["5 - 0", "2 - 0", "0 - 2", "4 - 0", "3 - 1", "3 - 1"], ["Friendly", "Friendly", "FIFA World Cup\u2122 Qualifier", "FIFA World Cup\u2122 Qualifier", "Friendly", "Friendly"]], "1891": [[], [], [], [], []], "gemiddelde elo": 1461, "2005": [[1111795200000, 1117152000000, 1117843200000, 1118448000000, 1118793600000, 1119052800000, 1119312000000, 1124236800000, 1125705600000, 1128729600000, 1131667200000, 1132099200000], [1560, 1568, 1578, 1591, 1582, 1559, 1611, 1616, 1630, 1624, 1619, 1630], ["Tunisia - Malawi", "Tunisia - Angola", "Botswana - Tunisia", "Tunisia - Guinea", "Argentina - Tunisia", "Tunisia - Germany", "Australia - Tunisia", "Tunisia - Kenya", "Kenya - Tunisia", "Tunisia - Morocco", "Congo DR - Tunisia", "Egypt - Tunisia"], ["7 - 0", "4 - 1", "1 - 3", "2 - 0", "2 - 1", "0 - 3", "0 - 2", "1 - 0", "0 - 2", "2 - 2", "2 - 2", "1 - 2"], ["FIFA World Cup\u2122 Qualifier", "Friendly", "FIFA World Cup\u2122 Qualifier", "FIFA World Cup\u2122 Qualifier", "FIFA Confederations Cup", "FIFA Confederations Cup", "FIFA Confederations Cup", "FIFA World Cup\u2122 Qualifier", "FIFA World Cup\u2122 Qualifier", "FIFA World Cup\u2122 Qualifier", "Friendly", "Friendly"]], "1911": [[], [], [], [], []], "1979": [[288144000000, 304646400000, 306892800000, 315014400000], [1533, 1537, 1534, 1540], ["Tunisia - Poland", "Tunisia - Malta", "Algeria - Tunisia", "Tunisia - Senegal"], ["0 - 2", "4 - 0", "1 - 1", "3 - 1"], ["Friendly", "Friendly", "Friendly", "Friendly"]], "1888": [[], [], [], [], []], "1895": [[], [], [], [], []], "2003": [[1045008000000, 1048723200000, 1048982400000, 1051660800000, 1061337600000, 1063152000000, 1065571200000, 1065830400000, 1069200000000], [1510, 1516, 1528, 1539, 1534, 1541, 1534, 1533, 1547], ["Tunisia - Sweden", "Tunisia - Ghana", "Tunisia - Cameroon", "Tunisia - Senegal", "Tunisia - Guinea", "Tunisia - C\u00f4te d'Ivoire", "Tunisia - Japan", "Tunisia - Morocco", "Tunisia - South Africa"], ["1 - 0", "8 - 7", "1 - 0", "1 - 0", "0 - 0", "3 - 2", "0 - 1", "0 - 0", "2 - 0"], ["Friendly", "Friendly", "Friendly", "Friendly", "Friendly", "Friendly", "Friendly", "Friendly", "Friendly"]], "1947": [[], [], [], [], []], "1887": [[], [], [], [], []], "2007": [[1170806400000, 1174694400000, 1180742400000, 1181952000000, 1187740800000, 1189296000000, 1192579200000, 1195257600000, 1195603200000], [1541, 1549, 1552, 1555, 1552, 1524, 1532, 1535, 1535], ["Morocco - Tunisia", "Seychelles - Tunisia", "Tunisia - Seychelles", "Tunisia - Mauritius", "Tunisia - Guinea", "Sudan - Tunisia", "United Arab Emirates - Tunisia", "Tunisia - Namibia", "Austria - Tunisia"], ["1 - 1", "0 - 3", "4 - 0", "2 - 0", "1 - 1", "3 - 2", "0 - 1", "2 - 0", "0 - 0"], ["Friendly", "Continental Qualifier", "Continental Qualifier", "Continental Qualifier", "Friendly", "Continental Qualifier", "Friendly", "Friendly", "Friendly"]], "1912": [[], [], [], [], []], "1901": [[], [], [], [], []], "1975": [[157766400000, 162950400000, 164937600000, 165974400000, 173836800000, 177379200000, 178675200000, 179193600000, 188179200000, 188524800000], [1396, 1400, 1391, 1413, 1423, 1401, 1403, 1405, 1414, 1416], ["Iraq - Tunisia", "Morocco - Tunisia", "Tunisia - Algeria", "Algeria - Tunisia", "Tunisia - Sudan", "Sudan - Tunisia", "Tunisia - Morocco", "Tunisia - Morocco", "Tunisia - United Arab Emirates", "Tunisia - Iraq"], ["0 - 0", "0 - 0", "1 - 1", "1 - 2", "3 - 2", "2 - 1", "0 - 0", "1 - 1", "3 - 0", "1 - 1"], ["Friendly", "Friendly", "Continental Qualifier", "Continental Qualifier", "Continental Qualifier", "Continental Qualifier", "Friendly", "Friendly", "Friendly", "Friendly"]], "1958": [[], [], [], [], []], "1964": [[-177552000000, -163036800000, -158198400000], [1310, 1302, 1294], ["Tunisia - Ethiopia", "Turkey - Tunisia", "Algeria - Tunisia"], ["3 - 2", "4 - 1", "1 - 0"], ["Friendly", "Friendly", "Friendly"]], "1944": [[], [], [], [], []], "1940": [[], [], [], [], []], "1994": [[758937600000, 760665600000, 760838400000, 761011200000, 763862400000, 764640000000, 764985600000, 784252800000, 784684800000, 787536000000], [1498, 1492, 1486, 1460, 1465, 1417, 1416, 1436, 1422, 1433], ["Tunisia - Netherlands", "Malta - Tunisia", "Slovenia - Tunisia", "Tunisia - Georgia", "Tunisia - Niger", "Tunisia - Mali", "Tunisia - Zaire", "Tunisia - C\u00f4te d'Ivoire", "Tunisia - Togo", "Tunisia - Algeria"], ["2 - 2", "1 - 1", "2 - 2", "0 - 2", "4 - 2", "0 - 2", "1 - 1", "2 - 0", "1 - 1", "1 - 0"], ["Friendly", "Friendly", "Friendly", "Friendly", "Friendly", "Continental Final", "Continental Final", "Friendly", "Continental Qualifier", "Friendly"]], "1942": [[], [], [], [], []], "1995": [[789004800000, 789436800000, 791337600000, 792374400000, 797817600000, 798595200000, 802224000000, 805766400000, 806371200000, 807062400000, 815529600000, 815702400000, 817603200000, 819676800000], [1449, 1444, 1448, 1435, 1427, 1403, 1417, 1438, 1429, 1418, 1433, 1435, 1446, 1435], ["Tunisia - Egypt", "Senegal - Tunisia", "Tunisia - Mauritania", "Tunisia - Liberia", "Egypt - Tunisia", "Liberia - Tunisia", "Togo - Tunisia", "Tunisia - Senegal", "Algeria - Tunisia", "Mauritania - Tunisia", "Tunisia - Algeria", "Tunisia - Mauritania", "Tunisia - Burkina Faso", "Zambia - Tunisia"], ["2 - 0", "0 - 0", "1 - 0", "0 - 0", "1 - 0", "1 - 0", "0 - 1", "4 - 0", "2 - 1", "0 - 0", "2 - 0", "2 - 1", "3 - 0", "2 - 0"], ["Friendly", "Continental Qualifier", "Continental Qualifier", "Continental Qualifier", "Friendly", "Continental Qualifier", "Continental Qualifier", "Continental Qualifier", "Friendly", "Continental Qualifier", "Friendly", "Friendly", "Friendly", "Friendly"]], "1903": [[], [], [], [], []], "2004": [[1074038400000, 1074297600000, 1074902400000, 1075248000000, 1075593600000, 1076112000000, 1076457600000, 1076716800000, 1080691200000, 1083110400000, 1085875200000, 1086393600000, 1087689600000, 1092787200000, 1094256000000, 1097280000000], [1551, 1554, 1561, 1585, 1574, 1604, 1607, 1634, 1611, 1617, 1602, 1606, 1580, 1558, 1565, 1552], ["Tunisia - Benin", "Tunisia - Benin", "Tunisia - Rwanda", "Tunisia - Congo DR", "Tunisia - Guinea", "Tunisia - Senegal", "Tunisia - Nigeria", "Tunisia - Morocco", "Tunisia - C\u00f4te d'Ivoire", "Tunisia - Mali", "Tunisia - Italy", "Tunisia - Botswana", "Guinea - Tunisia", "Tunisia - South Africa", "Morocco - Tunisia", "Malawi - Tunisia"], ["2 - 0", "2 - 1", "2 - 1", "3 - 0", "1 - 1", "1 - 0", "1 - 1", "2 - 1", "0 - 2", "1 - 0", "0 - 4", "4 - 1", "2 - 1", "0 - 2", "1 - 1", "2 - 2"], ["Friendly", "Friendly", "Continental Final", "Continental Final", "Continental Final", "Continental Final", "Continental Final", "Continental Final", "Friendly", "Friendly", "Friendly", "FIFA World Cup\u2122 Qualifier", "FIFA World Cup\u2122 Qualifier", "Friendly", "FIFA World Cup\u2122 Qualifier", "FIFA World Cup\u2122 Qualifier"]], "1959": [[-341452800000], [1298], ["Tunisia - Malta"], ["0 - 0"], ["Friendly"]], "laagste elo": 1216, "2001": [[979344000000, 980640000000, 983059200000, 985392000000, 989020800000, 990316800000, 991440000000, 992649600000, 993945600000, 995155200000, 1006905600000, 1009670400000], [1507, 1521, 1538, 1517, 1533, 1528, 1521, 1533, 1545, 1567, 1572, 1581], ["Tunisia - Morocco", "Congo - Tunisia", "Tunisia - Congo DR", "Morocco - Tunisia", "Madagascar - Tunisia", "Tunisia - C\u00f4te d'Ivoire", "Gabon - Tunisia", "Tunisia - Kenya", "Tunisia - Congo", "Congo DR - Tunisia", "Tunisia - Togo", "Tunisia - Liberia"], ["0 - 1", "1 - 2", "6 - 0", "2 - 0", "0 - 2", "1 - 1", "1 - 1", "4 - 1", "6 - 0", "0 - 3", "1 - 0", "7 - 2"], ["Continental Qualifier", "FIFA World Cup\u2122 Qualifier", "FIFA World Cup\u2122 Qualifier", "Continental Qualifier", "FIFA World Cup\u2122 Qualifier", "FIFA World Cup\u2122 Qualifier", "Continental Qualifier", "Continental Qualifier", "FIFA World Cup\u2122 Qualifier", "FIFA World Cup\u2122 Qualifier", "Friendly", "Friendly"]], "1878": [[], [], [], [], []], "1943": [[], [], [], [], []], "1949": [[], [], [], [], []], "1936": [[], [], [], [], []], "1952": [[], [], [], [], []], "1969": [[-21513600000, -19699200000, -17452800000, -14169600000, -10281600000], [1309, 1317, 1315, 1299, 1290], ["Tunisia - Morocco", "Morocco - Tunisia", "Tunisia - Morocco", "Congo - Tunisia", "Libya - Tunisia"], ["0 - 0", "0 - 0", "2 - 2", "4 - 1", "3 - 2"], ["FIFA World Cup\u2122 Qualifier", "FIFA World Cup\u2122 Qualifier", "FIFA World Cup\u2122 Qualifier", "Friendly", "Friendly"]], "1960": [[-315446400000, -296784000000, -289440000000, -288230400000, -286416000000, -286070400000], [1295, 1296, 1281, 1298, 1278, 1270], ["Tunisia - Yugoslavia", "Yugoslavia - Tunisia", "Morocco - Tunisia", "Tunisia - Morocco", "Tunisia - German DR", "Malta - Tunisia"], ["1 - 5", "7 - 0", "2 - 1", "2 - 1", "0 - 3", "1 - 0"], ["Friendly", "Friendly", "FIFA World Cup\u2122 Qualifier", "FIFA World Cup\u2122 Qualifier", "Friendly", "Friendly"]], "1981": [[352598400000, 352857600000, 355881600000, 357091200000, 370396800000, 372729600000, 374025600000, 378259200000, 378432000000], [1519, 1527, 1534, 1528, 1529, 1511, 1506, 1511, 1518], ["Bahrain - Tunisia", "Saudi Arabia - Tunisia", "Tunisia - Senegal", "Senegal - Tunisia", "Morocco - Tunisia", "Tunisia - Malta", "Tunisia - Cameroon", "United Arab Emirates - Tunisia", "United Arab Emirates - Tunisia"], ["0 - 3", "1 - 2", "1 - 0", "0 - 0", "2 - 2", "0 - 1", "1 - 1", "1 - 2", "1 - 4"], ["Friendly", "Friendly", "Continental Qualifier", "Continental Qualifier", "Friendly", "Friendly", "Friendly", "Friendly", "Friendly"]], "1973": [[97632000000, 98236800000, 99446400000, 106012800000, 108172800000, 114048000000, 114220800000, 114566400000, 114912000000, 115171200000, 125452800000, 126057600000], [1342, 1342, 1331, 1323, 1322, 1338, 1350, 1361, 1378, 1393, 1404, 1405], ["Tunisia - Yugoslavia", "Tunisia - C\u00f4te d'Ivoire", "C\u00f4te d'Ivoire - Tunisia", "Algeria - Tunisia", "Tunisia - Brazil", "Tunisia - Syria", "Tunisia - Egypt", "Tunisia - Yemen PDR", "Tunisia - Iraq", "Tunisia - Syria", "Congo - Tunisia", "Guinea - Tunisia"], ["0 - 5", "1 - 1", "2 - 1", "2 - 1", "1 - 4", "4 - 1", "1 - 0", "2 - 0", "2 - 0", "4 - 0", "0 - 1", "0 - 0"], ["Friendly", "FIFA World Cup\u2122 Qualifier", "FIFA World Cup\u2122 Qualifier", "Friendly", "Friendly", "Friendly", "Friendly", "Friendly", "Friendly", "Friendly", "Friendly", "Friendly"]], "1966": [[], [], [], [], []], "1915": [[], [], [], [], []], "1956": [[], [], [], [], []], "1948": [[], [], [], [], []], "1998": [[885945600000, 886204800000, 886550400000, 886982400000, 887241600000, 887587200000, 888019200000, 894067200000, 896227200000, 896572800000, 897091200000, 897868800000, 898473600000, 898819200000, 907459200000, 910396800000, 910656000000], [1540, 1548, 1554, 1498, 1512, 1526, 1513, 1509, 1502, 1494, 1505, 1492, 1469, 1488, 1493, 1488, 1496], ["Tunisia - Yugoslavia", "Tunisia - Guinea", "Mali - Tunisia", "Ghana - Tunisia", "Tunisia - Congo DR", "Tunisia - Togo", "Tunisia - Burkina Faso", "Tunisia - Georgia", "Austria - Tunisia", "Tunisia - Chile", "Tunisia - Wales", "England - Tunisia", "Colombia - Tunisia", "Romania - Tunisia", "Tunisia - Liberia", "Tunisia - Zimbabwe", "Tunisia - Latvia"], ["0 - 3", "4 - 1", "0 - 1", "2 - 0", "2 - 1", "3 - 1", "1 - 1", "1 - 1", "2 - 1", "2 - 3", "4 - 0", "2 - 0", "1 - 0", "1 - 1", "2 - 1", "1 - 1", "3 - 0"], ["Friendly", "Friendly", "Friendly", "Continental Final", "Continental Final", "Continental Final", "Continental Final", "Friendly", "Friendly", "Friendly", "Friendly", "FIFA World Cup\u2122 Final", "FIFA World Cup\u2122 Final", "FIFA World Cup\u2122 Final", "Continental Qualifier", "Friendly", "Friendly"]], "1934": [[], [], [], [], []], "1929": [[], [], [], [], []], "1917": [[], [], [], [], []], "1914": [[], [], [], [], []], "1927": [[], [], [], [], []], "1978": [[253497600000, 254534400000, 257990400000, 258249600000, 258422400000, 258681600000, 260582400000, 264384000000, 265593600000, 265939200000, 266284800000, 282873600000], [1512, 1515, 1513, 1537, 1523, 1493, 1488, 1483, 1549, 1535, 1559, 1542], ["Libya - Tunisia", "Tunisia - Libya", "Morocco - Tunisia", "Tunisia - Uganda", "Congo - Tunisia", "Ghana - Tunisia", "Tunisia - Netherlands", "France - Tunisia", "Tunisia - Mexico", "Poland - Tunisia", "Germany FR - Tunisia", "Syria - Tunisia"], ["0 - 0", "2 - 1", "1 - 1", "3 - 1", "0 - 0", "1 - 0", "0 - 4", "2 - 0", "3 - 1", "1 - 0", "0 - 0", "2 - 1"], ["Friendly", "Friendly", "Continental Final", "Continental Final", "Continental Final", "Continental Final", "Friendly", "Friendly", "FIFA World Cup\u2122 Final", "FIFA World Cup\u2122 Final", "FIFA World Cup\u2122 Final", "Friendly"]], "1950": [[], [], [], [], []], "2006": [[1137024000000, 1137283200000, 1137888000000, 1138233600000, 1138579200000, 1139011200000, 1141171200000, 1148947200000, 1149206400000, 1150243200000, 1150675200000, 1151020800000, 1155686400000, 1157241600000, 1160179200000, 1163548800000], [1633, 1640, 1660, 1674, 1610, 1615, 1600, 1607, 1608, 1600, 1581, 1556, 1541, 1528, 1532, 1538], ["Tunisia - Libya", "Tunisia - Ghana", "Tunisia - Zambia", "Tunisia - South Africa", "Tunisia - Guinea", "Nigeria - Tunisia", "Tunisia - Serbia and Montenegro", "Tunisia - Belarus", "Tunisia - Uruguay", "Tunisia - Saudi Arabia", "Spain - Tunisia", "Ukraine - Tunisia", "Tunisia - Mali", "Mauritius - Tunisia", "Tunisia - Sudan", "Tunisia - Libya"], ["1 - 0", "2 - 0", "4 - 1", "2 - 0", "0 - 3", "1 - 1", "0 - 1", "3 - 0", "0 - 0", "2 - 2", "3 - 1", "1 - 0", "0 - 1", "0 - 0", "1 - 0", "2 - 0"], ["Friendly", "Friendly", "Continental Final", "Continental Final", "Continental Final", "Continental Final", "Friendly", "Friendly", "Friendly", "FIFA World Cup\u2122 Final", "FIFA World Cup\u2122 Final", "FIFA World Cup\u2122 Final", "Friendly", "Continental Qualifier", "Continental Qualifier", "Friendly"]], "1967": [[-92880000000, -91670400000, -90460800000, -75081600000, -73094400000, -65836800000], [1329, 1352, 1347, 1313, 1327, 1307], ["Tunisia - Turkey", "Tunisia - Cameroon", "Tunisia - Congo", "Cameroon - Tunisia", "Tunisia - Libya", "Saudi Arabia - Tunisia"], ["0 - 0", "4 - 0", "1 - 1", "2 - 0", "3 - 0", "4 - 0"], ["Friendly", "Continental Qualifier", "Continental Qualifier", "Continental Qualifier", "Friendly", "Friendly"]], "1886": [[], [], [], [], []], "1930": [[], [], [], [], []], "1983": [[412905600000, 413683200000, 417225600000, 418780800000, 419990400000, 429667200000, 430876800000], [1427, 1420, 1428, 1438, 1447, 1430, 1426], ["Tunisia - Malta", "Tunisia - German DR", "Tunisia - Morocco", "Tunisia - Rwanda", "Rwanda - Tunisia", "Egypt - Tunisia", "Tunisia - Egypt"], ["2 - 1", "0 - 2", "1 - 0", "5 - 0", "0 - 1", "1 - 0", "0 - 0"], ["Friendly", "Friendly", "Friendly", "Continental Qualifier", "Continental Qualifier", "Continental Qualifier", "Continental Qualifier"]], "1873": [[], [], [], [], []], "2013": [[1357516800000, 1357776000000, 1358035200000, 1358812800000, 1359158400000, 1359504000000, 1363996800000, 1370649600000, 1371340800000, 1373068800000, 1373760000000, 1376438400000, 1378512000000, 1381622400000, 1384646400000], [1500, 1499, 1490, 1513, 1496, 1486, 1493, 1486, 1475, 1463, 1463, 1473, 1495, 1491, 1465], ["Tunisia - Ethiopia", "Gabon - Tunisia", "Ghana - Tunisia", "Tunisia - Algeria", "C\u00f4te d'Ivoire - Tunisia", "Togo - Tunisia", "Tunisia - Sierra Leone", "Sierra Leone - Tunisia", "Equatorial Guinea - Tunisia", "Tunisia - Morocco", "Morocco - Tunisia", "Tunisia - Congo", "Tunisia - Cape Verde Islands", "Tunisia - Cameroon", "Cameroon - Tunisia"], ["1 - 1", "1 - 1", "4 - 2", "1 - 0", "3 - 0", "1 - 1", "2 - 1", "2 - 2", "1 - 1", "0 - 1", "0 - 0", "3 - 0", "3 - 0", "0 - 0", "4 - 1"], ["Friendly", "Friendly", "Friendly", "Continental Final", "Continental Final", "Continental Final", "FIFA World Cup\u2122 Qualifier", "FIFA World Cup\u2122 Qualifier", "FIFA World Cup\u2122 Qualifier", "Friendly", "Friendly", "Friendly", "FIFA World Cup\u2122 Qualifier", "FIFA World Cup\u2122 Qualifier", "FIFA World Cup\u2122 Qualifier"]], "1999": [[916963200000, 918604800000, 920160000000, 923702400000, 928627200000, 929836800000, 940032000000, 941328000000, 941500800000, 945820800000], [1514, 1509, 1523, 1541, 1554, 1506, 1512, 1521, 1520, 1531], ["Algeria - Tunisia", "Tunisia - Sweden", "Tunisia - Uganda", "Uganda - Tunisia", "Tunisia - Algeria", "Liberia - Tunisia", "Tunisia - United Arab Emirates", "Tunisia - Zambia", "Tunisia - Zambia", "Tunisia - Ghana"], ["0 - 1", "0 - 1", "6 - 0", "0 - 2", "2 - 0", "2 - 0", "1 - 0", "2 - 1", "0 - 0", "2 - 0"], ["Continental Qualifier", "Friendly", "Continental Qualifier", "Continental Qualifier", "Continental Qualifier", "Continental Qualifier", "Friendly", "Friendly", "Friendly", "Friendly"]], "1881": [[], [], [], [], []], "1953": [[], [], [], [], []], "1894": [[], [], [], [], []], "1921": [[], [], [], [], []], "1893": [[], [], [], [], []], "1876": [[], [], [], [], []], "1902": [[], [], [], [], []], "1997": [[852336000000, 853027200000, 854236800000, 860284800000, 862099200000, 865036800000, 865728000000, 868060800000, 868752000000, 870912000000, 871084800000, 871776000000, 875664000000, 878688000000], [1508, 1523, 1498, 1508, 1516, 1503, 1504, 1508, 1517, 1530, 1547, 1556, 1545, 1548], ["Tunisia - Algeria", "Tunisia - Egypt", "Guinea - Tunisia", "Namibia - Tunisia", "Tunisia - Liberia", "Tunisia - Algeria", "Egypt - Tunisia", "Tunisia - Mali", "Tunisia - Guinea", "Tunisia - Zambia", "Tunisia - Nigeria", "Tunisia - Namibia", "Tunisia - Australia", "Tunisia - Bosnia and Herzegovina"], ["0 - 0", "1 - 0", "1 - 0", "1 - 2", "2 - 0", "0 - 1", "0 - 0", "1 - 0", "1 - 0", "3 - 1", "2 - 0", "4 - 0", "0 - 3", "2 - 1"], ["Friendly", "FIFA World Cup\u2122 Qualifier", "Continental Qualifier", "FIFA World Cup\u2122 Qualifier", "FIFA World Cup\u2122 Qualifier", "Friendly", "FIFA World Cup\u2122 Qualifier", "Friendly", "Continental Qualifier", "Friendly", "Friendly", "FIFA World Cup\u2122 Qualifier", "Friendly", "Friendly"]], "1961": [[-279504000000, -255398400000, -254361600000], [1275, 1259, 1255], ["Morocco - Tunisia", "Nigeria - Tunisia", "Tunisia - Nigeria"], ["1 - 1", "2 - 1", "2 - 2"], ["FIFA World Cup\u2122 Qualifier", "Continental Qualifier", "Continental Qualifier"]], "1992": [[698716800000, 699062400000, 703900800000, 717206400000, 718761600000, 719971200000, 721094400000, 724809600000], [1399, 1414, 1409, 1411, 1418, 1414, 1412, 1410], ["Tunisia - Nigeria", "Tunisia - Belgium", "Tunisia - Sweden", "Tunisia - Algeria", "Tunisia - Benin", "Ethiopia - Tunisia", "Tunisia - Finland", "Tunisia - Morocco"], ["1 - 1", "2 - 1", "0 - 1", "1 - 1", "5 - 1", "0 - 0", "1 - 1", "1 - 1"], ["Friendly", "Friendly", "Friendly", "Friendly", "FIFA World Cup\u2122 Qualifier", "FIFA World Cup\u2122 Qualifier", "Friendly", "FIFA World Cup\u2122 Qualifier"]], "1874": [[], [], [], [], []], "1905": [[], [], [], [], []], "2008": [[1199577600000, 1199750400000, 1201046400000, 1201392000000, 1201737600000, 1202083200000, 1206489600000, 1212278400000, 1212796800000, 1213488000000, 1214006400000, 1219190400000, 1220659200000, 1223683200000, 1223942400000, 1227052800000], [1521, 1527, 1529, 1554, 1548, 1530, 1547, 1511, 1516, 1524, 1527, 1523, 1515, 1518, 1513, 1517], ["Tunisia - Zambia", "Tunisia - Zambia", "Tunisia - Senegal", "Tunisia - South Africa", "Tunisia - Angola", "Tunisia - Cameroon", "Tunisia - C\u00f4te d'Ivoire", "Tunisia - Burkina Faso", "Seychelles - Tunisia", "Burundi - Tunisia", "Tunisia - Burundi", "Tunisia - Angola", "Burkina Faso - Tunisia", "Tunisia - Seychelles", "France - Tunisia", "Ghana - Tunisia"], ["1 - 2", "1 - 0", "2 - 2", "3 - 1", "0 - 0", "2 - 3", "2 - 0", "1 - 2", "0 - 2", "0 - 1", "2 - 1", "1 - 1", "0 - 0", "5 - 0", "3 - 1", "0 - 0"], ["Friendly", "Friendly", "Continental Final", "Continental Final", "Continental Final", "Continental Final", "Friendly", "FIFA World Cup\u2122 Qualifier", "FIFA World Cup\u2122 Qualifier", "FIFA World Cup\u2122 Qualifier", "FIFA World Cup\u2122 Qualifier", "Friendly", "FIFA World Cup\u2122 Qualifier", "FIFA World Cup\u2122 Qualifier", "Friendly", "Friendly"]], "1989": [[600220800000, 601430400000, 605923200000, 607651200000, 612403200000, 612835200000, 613526400000, 613958400000, 614736000000, 616550400000, 617760000000, 618278400000, 618969600000, 620179200000, 623808000000, 625881600000, 626400000000, 627436800000], [1309, 1336, 1340, 1334, 1329, 1323, 1314, 1320, 1339, 1320, 1302, 1319, 1331, 1353, 1343, 1347, 1335, 1323], ["Zaire - Tunisia", "Tunisia - Morocco", "Tunisia - Egypt", "Algeria - Tunisia", "Egypt - Tunisia", "Malawi - Tunisia", "Zambia - Tunisia", "Egypt - Tunisia", "Tunisia - Zaire", "Senegal - Tunisia", "Tunisia - Senegal", "Tunisia - Malawi", "Morocco - Tunisia", "Tunisia - Zambia", "Cameroon - Tunisia", "Tunisia - Algeria", "Tunisia - Egypt", "Tunisia - Cameroon"], ["3 - 1", "2 - 1", "0 - 0", "2 - 0", "1 - 0", "1 - 0", "1 - 0", "1 - 1", "1 - 0", "3 - 0", "0 - 1", "3 - 0", "0 - 0", "1 - 0", "2 - 0", "0 - 0", "0 - 4", "0 - 1"], ["FIFA World Cup\u2122 Qualifier", "FIFA World Cup\u2122 Qualifier", "Friendly", "Friendly", "Friendly", "Friendly", "FIFA World Cup\u2122 Qualifier", "Friendly", "FIFA World Cup\u2122 Qualifier", "Continental Qualifier", "Continental Qualifier", "Friendly", "FIFA World Cup\u2122 Qualifier", "FIFA World Cup\u2122 Qualifier", "FIFA World Cup\u2122 Qualifier", "Friendly", "Friendly", "FIFA World Cup\u2122 Qualifier"]], "1883": [[], [], [], [], []], "2000": [[947203200000, 948585600000, 949104000000, 949536000000, 949881600000, 950140800000, 950313600000, 952819200000, 955065600000, 956361600000, 960681600000, 961286400000, 962150400000, 963014400000, 967939200000, 970876800000, 974246400000], [1537, 1500, 1511, 1525, 1553, 1501, 1502, 1508, 1514, 1518, 1527, 1528, 1524, 1530, 1521, 1532, 1530], ["Tunisia - Togo", "Nigeria - Tunisia", "Tunisia - Morocco", "Tunisia - Congo", "Egypt - Tunisia", "Cameroon - Tunisia", "Tunisia - South Africa", "USA - Tunisia", "Mauritania - Tunisia", "Tunisia - Mauritania", "Tunisia - Senegal", "C\u00f4te d'Ivoire - Tunisia", "Tunisia - Algeria", "Tunisia - Madagascar", "Kenya - Tunisia", "Tunisia - Gabon", "Tunisia - Switzerland"], ["7 - 0", "4 - 2", "0 - 0", "1 - 0", "0 - 1", "3 - 0", "2 - 2", "1 - 1", "1 - 2", "3 - 0", "4 - 1", "2 - 2", "2 - 2", "1 - 0", "0 - 0", "4 - 2", "1 - 1"], ["Friendly", "Continental Final", "Continental Final", "Continental Final", "Continental Final", "Continental Final", "Continental Final", "Friendly", "FIFA World Cup\u2122 Qualifier", "FIFA World Cup\u2122 Qualifier", "Friendly", "FIFA World Cup\u2122 Qualifier", "Friendly", "FIFA World Cup\u2122 Qualifier", "Continental Qualifier", "Continental Qualifier", "Friendly"]], "1875": [[], [], [], [], []], "1877": [[], [], [], [], []], "1988": [[571449600000, 571708800000, 572140800000, 584409600000, 584755200000, 585100800000, 586742400000, 588124800000, 593222400000, 594691200000, 596246400000, 598406400000, 598579200000], [1333, 1322, 1313, 1320, 1316, 1317, 1350, 1318, 1315, 1329, 1324, 1330, 1327], ["Tunisia - Malta", "Finland - Tunisia", "Bahrain - Tunisia", "Iraq - Tunisia", "Egypt - Tunisia", "Lebanon - Tunisia", "Tunisia - Guinea", "Guinea - Tunisia", "Republic of Ireland - Tunisia", "Tunisia - Algeria", "Saudi Arabia - Tunisia", "C\u00f4te d'Ivoire - Tunisia", "Liberia - Tunisia"], ["1 - 2", "3 - 0", "1 - 0", "1 - 1", "1 - 0", "1 - 1", "5 - 0", "3 - 0", "4 - 0", "1 - 0", "1 - 0", "1 - 1", "1 - 1"], ["Friendly", "Friendly", "Friendly", "Friendly", "Friendly", "Friendly", "FIFA World Cup\u2122 Qualifier", "FIFA World Cup\u2122 Qualifier", "Friendly", "Friendly", "Friendly", "Friendly", "Friendly"]], "1962": [[-251337600000, -250819200000], [1216, 1266], ["Ethiopia - Tunisia", "Tunisia - Uganda"], ["4 - 2", "3 - 0"], ["Continental Final", "Continental Final"]], "1955": [[], [], [], [], []], "1926": [[], [], [], [], []], "1904": [[], [], [], [], []]}}