{"time": ["21:20", "22:46", "00:40", "01:53", "02:51", "05:28", null, null, null, null, null, null, null, null, null, null], "name": "Koenraad Van Den Eeckhout", "speed_total": 4.8, "time_total": "", "speed": [0, 5.0, 4.8, 5.0, 5.7, 4.5, 3.7, 0, 0, 0, 0, 0, 0, 0, 0, 0], "position": 10115, "time_graph": ["2015-08-14T21:20:00", "2015-08-14T22:46:00", "2015-08-15T00:40:00", "2015-08-15T01:53:00", "2015-08-15T02:51:00", "2015-08-15T05:28:00", null, null, null, null, null, null, null, null, null, null]}