{"time": ["21:21", "22:59", "01:15", "02:38", "03:42", "05:54", "08:42", null, null, null, null, null, null, null, null, null], "name": "Geert Schoenmaekers", "speed_total": 4.7, "time_total": "", "speed": [0, 4.8, 4.4, 4.8, 3.6, 0, 0, 0, 0, 0, 0, 0, 0, 0, 0, 0], "position": 10695, "time_graph": ["2015-08-14T21:21:00", "2015-08-14T22:59:00", "2015-08-15T01:15:00", "2015-08-15T02:38:00", "2015-08-15T03:42:00", "2015-08-15T05:54:00", "2015-08-15T08:42:00", null, null, null, null, null, null, null, null, null]}