{"time": ["21:07", "22:34", "00:34", "02:05", "03:05", "05:24", "08:03", null, null, null, null, null, null, null, null, null], "name": "Geert Vanlangenaker", "speed_total": 4.7, "time_total": "", "speed": [0, 5.5, 4.2, 4.5, 4.6, 4.1, 0, 0, 0, 0, 0, 0, 0, 0, 0, 0], "position": 9456, "time_graph": ["2015-08-14T21:07:00", "2015-08-14T22:34:00", "2015-08-15T00:34:00", "2015-08-15T02:05:00", "2015-08-15T03:05:00", "2015-08-15T05:24:00", "2015-08-15T08:03:00", null, null, null, null, null, null, null, null, null]}