{"time": ["21:00", "22:22", "00:20", "02:02", "03:13", "05:58", "08:55", null, null, null, null, null, null, null, null, null], "name": "Jan Spoelma", "speed_total": 4.7, "time_total": "", "speed": [0, 5.1, 4.2, 5.4, 4.8, 4.9, 3.7, 4.4, 0, 0, 0, 0, 0, 0, 0, 0], "position": 9643, "time_graph": ["2015-08-14T21:00:00", "2015-08-14T22:22:00", "2015-08-15T00:20:00", "2015-08-15T02:02:00", "2015-08-15T03:13:00", "2015-08-15T05:58:00", "2015-08-15T08:55:00", null, null, null, null, null, null, null, null, null]}