{"time": ["21:17", "22:45", "01:02", "02:34", "03:47", "05:42", "08:02", "09:31", "10:49", null, null, null, null, null, null, null], "name": "Jef Merckx", "speed_total": 0.0, "time_total": "", "speed": [0, 0, 0, 0, 0, 0, 0, 0, 0, 0, 0, 0, 0, 0, 0, 0], "position": 9651, "time_graph": ["2015-08-14T21:17:00", "2015-08-14T22:45:00", "2015-08-15T01:02:00", "2015-08-15T02:34:00", "2015-08-15T03:47:00", "2015-08-15T05:42:00", "2015-08-15T08:02:00", "2015-08-15T09:31:00", "2015-08-15T10:49:00", null, null, null, null, null, null, null]}