{"1991-10": {"Total Votes": 287604.0, "Parties": ["suyuz na demokratichnite sili - tsentur", "bsp+", "suyuz na demokratichnite sili", "dvizhenie za prava i svobodi", "bulgarski zemedelski naroden suyuz - 'nikola petkov'", "konfederatsiya 'tsarstvo bulgariya'", "suyuz na demokratichniti sili - liberali", "bulgarski zemedelski naroden suyuz (edinen)", "bulgarska biznes partiya", "bulgarska natsionalna radikalna partiya", "koalitsiya za turnovska konstitutsiya 'svoboda'", "politicheski forum 'preobrazhenie'", "dvizhenie 'bezpartiini za demokratsiya'", "bulgarska komunisticheska partiya", "suyuz na bezpartiinite garanti", "organizatsiya na surdechno bolnite i sotsialno slabite grazhdani v bulgariya", "svobodna kooperativna partiya", "koalitsiya bulgarski natisionalen suyuz", "bulgarska rabotnichesko-selska partiya", "liberalna partiya - pernik", "partiya 'liberalen kongres'", "bulgarska revolyutsionna mladezhka partiya", "partiya 'natsionalen patriotichen suyuz'", "bulgarska komunisticheska partiya - marksisti", "partiya na sobstvenitsite v bulgariya"], "Percent": [0.3878423109553414, 0.2938206700880377, 0.0521272304974896, 0.04637279036452901, 0.037092669086660826, 0.035555833715803675, 0.03541327658864272, 0.02602189121152696, 0.0204413012336407, 0.008417824508699462, 0.008396962490090542, 0.007166103392164226, 0.006182111514443471, 0.006084755427601842, 0.0045027190164253625, 0.0037482093434027344, 0.0037099623092863797, 0.003675192278271512, 0.0032683829153975605, 0.0032405668905856663, 0.002357408102808028, 0.0022878680407782924, 0.0021696499353277424, 7.997107133419563e-05, 2.4339021710407366e-05]}, "2009-7": {"Total Votes": 508469.0, "Parties": ["GERB", "COALITION FOR BULGARIA", "Ataka party", "Steering Committee - Valeria Plamenova Petrova - independent", "Blue Coalition", "Movement for Rights and Freedoms", "National Movement for Stability and Progress (former National Movement Simeon II)", "Order, Law, Justice", "Lider", "The Greens", "BULGARIAN left coalition", "For the Homeland - DGI-NL", "Bulgarian National Union - ND", "UNION OF BULGARIAN PATRIOTS (GBS)", "Union of Patriotic Forces and Reserve Soldiers Defense", "Social Democrats", "National Movement for the Salvation of the Fatherland", "The Other BULGARIA"], "Percent": [0.41547862308223316, 0.1687241503415154, 0.12903244838918398, 0.06787827773177912, 0.056563920317659486, 0.046876014073621006, 0.0427420354043216, 0.031773815119505805, 0.029256454179114162, 0.005437892968892893, 0.001567450523040736, 0.001126912358472198, 0.0010325113232075114, 0.0009577771702896341, 0.0005093722527823722, 0.00045037160574194296, 0.0003894042704668328, 0.00020256888817214027]}, "2001-6": {"Total Votes": 263976.0, "Parties": ["National Movement Simeon II (NMS)", "United Democratic Forces - UDF, People's Union: BAPU - PU and DP, BSDP, National MRF", "Coalition for Bulgaria", "George Day - IMRO", "MRF (MRF - Liberal Union - EuroRoma)", "Coalition Simeon II", "National Union for Tzar Simeon II", "Bulgarian Euroleft, BUSDP - United Socialdemocrats, BAPU", "Union Bulgaria", "Patriotism 2000", "George Ganchev's Block", "Independents", "Bulgarian Workers' Party (communists)", "NU Fatherland and Left", "Coalition National Union Tzar Kiro", "Bulgarian Workers' Socialist Party", "United Agrarian Forces (UAF) - National League - BAPU and BAPU Nikola Petkov", "Bulgarian Communist Party Fatherland", "Movement for Defense of Retired, Unemployed and Socially Weak Citizens - Front of the Progressive Forces in Bulgaria", "Democratic Party of Justice in RB", "Free Co-operative Party", "Union of Patriotic Forces and Reserve Soldiers Defense", "Bulgarian National Party Social Union", "Fatherland Party of Labor", "Bulgarian National-Radical Party"], "Percent": [0.4785131981695306, 0.1923659726641816, 0.12841697730096677, 0.04081810467618268, 0.03923083916719702, 0.03170363972482347, 0.026449374185532018, 0.010440343061490439, 0.009625875079552686, 0.006890777949510561, 0.005837651907749189, 0.00545882959056884, 0.003905658090129406, 0.0038336818498651394, 0.0030381549837864047, 0.0027881322544473742, 0.0019244173712761766, 0.0015645361699548443, 0.0014054307967390975, 0.0013599721186774555, 0.0012311725308361365, 0.0009811498014971058, 0.0009470557929508744, 0.000662939055065612, 0.0006061157074885596]}, "1994-12": {"Total Votes": 285519.0, "Parties": ["bspasek", "suyuz na demokratichnite sili", "bulgarski biznes blok", "bzns-tk", "politicheski suyuz 'demokratichna alternativa za republikata'", "dvizhenie za prava i svobodi", "patriotichen suyuz", "konfederatsiya 'tsarstvo bulgariya'", "suyuz 'nov izbor'", "bulgarska komunisticheska partiya", "natsionalno dvizhenie za koronovana demokratsiya 'tsarstvo bulgariya'", "suyuz na monarchicheskite sili 'tsarstvo bulgariya'", "bulgarska natsionalna radikalna partiya", "dvizhenie za zashchita na pensioneri, bezrabotni i sotsialno slabi grazhdani", "partiya na demokratichnite promeni", "organizatsiya na surdechno bolnite i sotsialno slabite grazhdani v bulgariya", "naroden suyuz", "forum 'preobrazhenie'", "suyuz na demokratichnite partii i dvizheniya 'era - 3'", "bulgarska rabotnichesko-selska partiya", "dvizhenie 'napred bulgariya", "demokraticheska partiya na spravedlivostta", "khristiyandemokratichen suyuz", "bulgarska liga za zashchita pravata na choveka i grazhdanina", "demokraticheska partiya v bulgariya", "obedinenie za sotsialisum", "svobodna demokraticheska partiya", "front na progresivnite sili v bulgariya", "svobodna kooperativna partiya", "bulgarska revolyutsionna mladezhka partiya", "republikanska partiya v bulgariya", "bulgarska otechestvena partiya - natsionalen suyuz", "narodnoliberalna partiya 'stefan stambolov'", "demokratichna partiya na truda", "suyuz na svobodnite demokrati", "partiya na sobstvenitsite v bulgariya", "partiya 'bulgarski orel'"], "Percent": [0.3706128138582721, 0.27224107677597637, 0.07886690552992971, 0.06359997057989135, 0.05457430153509924, 0.035286618403678915, 0.020601080838753286, 0.018608218717493408, 0.018152907512284648, 0.012577096445420445, 0.009498492219431982, 0.006910223137514491, 0.005015428045068804, 0.003425341220724365, 0.003124135346509339, 0.0027038480801627914, 0.002441168538696199, 0.001975350151828775, 0.0017091682164759613, 0.001656632308182643, 0.0015480580977097847, 0.0015340485221648997, 0.0014885174016440238, 0.001253857011267201, 0.0012468522234947586, 0.0011277708313632369, 0.0010997516802734668, 0.001057722953638812, 0.0010332061964352635, 0.0010297038025490423, 0.0007144883527891313, 0.0006724596261544766, 0.0006619524444958129, 0.0005533782340229546, 0.0005323638707056273, 0.00047282317463986635, 0.000392268115256778]}, "1997-4": {"Total Votes": 229454.0, "Parties": ["obedinenie na natsiyata - dvizhenie na onepravdanite", "demokratichna levitsa", "evrolevitsa", "obedinenie za tsarya", "bulgarski biznes blok", "bulgarska komunisticheska partiya", "partiya na bulgarskite zheni", "bulgarska khristiyanska koalitsiya", "koalitsiya 'napred bulgariya", "demokraticheska partiya na spravedlivostta", "bulgarski zemedelski naroden suyuz - tsentur", "politicheski suyuz 'demokratichna alternativa za republikata'", "khristiyandemokratichen suyuz", "partiya na demokratichnite promeni", "bulgarska rabotnicheska sotsialisticheska partiya", "bulgarska natsionalna demokraticheska partiya", "liberalen forum", "koronovana demokratsiya", "bulgarski zemedelski naroden suyuz - 'nikola petkov'", "bulgarska rabotnichesko-selska partiya", "bulgarska natsionalna radikalna partiya", "bulgarska revolyutsionna mladezhka partiya", "bulgarska partiya liberali", "independents", "narodna partiya", "demokraticheska liga", "bulgarska otechestvena partiya - natsionalen suyuz", "naroden patriotichen lyav front", "bulgarska demokraticheska partiya za evropeiski e svetovni shchati", "bulgarska zelena federatsiya", "bulgarska natsionalna ekologichna partiya - veliko turnovo", "suyuz na bulgarskite obshchnosti", "bulgarsko natsionalno dvizhenie na vechniya put", "obedinenie za natsionalno spasenie", "front na progresivnite sili v bulgariya"], "Percent": [0.5836028136358485, 0.16957647284423022, 0.06728581763665048, 0.05626400062757677, 0.054551239028301966, 0.01059907432426543, 0.010063019167240493, 0.006275767691999268, 0.0034429558865829318, 0.003281703522274617, 0.0026759176131163544, 0.002370845572533057, 0.0021878023481830783, 0.0021834441761747455, 0.0021790860041664122, 0.0017999250394414566, 0.0017868505234164582, 0.0017345524593164643, 0.0017084034272664673, 0.0016735380511998048, 0.001516643858899823, 0.0014251222467248337, 0.0012638698824165191, 0.0012333626783581895, 0.0012202881623331909, 0.0010590357980248765, 0.0009849468738832184, 0.0009805887018748856, 0.0009021416057248948, 0.0008847089176915635, 0.0008585598856415665, 0.00077139644547491, 0.0006493676292415909, 0.0005186224689916061, 0.0004881152649332764]}, "2005-6": {"Total Votes": 218553.0, "Parties": ["National Movement Simeon II (NMS)", "Coalition for Bulgaria", "Movement for Rights and Freedoms", "Ataka Party", "UDF - UDF Democratic Party Movement St. George Agrarian SC - Agrarian DROM", "Democrats for Strong BULGARIA (DSB)", "COALITION BULGARIAN NATIONAL UNION", "New Time (NV)", "COALITION OF ROSE (BSD PARTIES, AND NMRF GTN)", "Radoslav Nikolov Koev - Independent", "Nedelcho Mihaylov Dimov - Independent", "Euroroma", "BULGARIAN Christian Coalition (BHC)", "National Coalition Long Live Bulgaria! (DzB)", "Federation of Free Business (FSB-SB)", "The United Party of Pensioners BULGARIA (OPPB)", "Formation for Active Citizen Society (FAGO)", "Union of National Dignity GRANITE", "COALITION Dostojna Bulgaria", "MOVEMENT FORWARD BULGARIA", "CHAMBER OF EXPERTS", "Roden Kraj (Homeland)", "Popular Agrarian Party  Nikola Petkov", "Free Democratic Party - PSD"], "Percent": [0.27566768701413386, 0.25596537224380356, 0.08655108829437254, 0.08199384131080333, 0.07058699720433945, 0.060076960737212484, 0.053565954253659294, 0.033932272721033344, 0.0203703449506527, 0.017176611622810027, 0.012006241049081916, 0.006588790819618125, 0.005582169999954244, 0.004621304672093268, 0.0037382236802972276, 0.0032303377212849972, 0.0018439463196570167, 0.0015968666639213371, 0.0015282334262169818, 0.0013818158524476901, 0.0009196853852383632, 0.0004117994262261328, 0.0003614683852429388, 0.00030198624589916406]}}